[
  {
    "_id": { "$oid": "693e36d08bebd27195925001" },
    "topic": "BODY_PARTS",
    "level": "N5",
    "setNumber": 1,
    "title": "Bộ phận cơ thể - Cơ bản",
    "description": "Bộ câu hỏi BODY_PARTS cấp độ N5",
    "questions": [
      {
        "_id": { "$oid": "693e36d08bebd27195925002" },
        "questionNumber": 1,
        "questionType": "MULTIPLE_CHOICE",
        "questionText": "「頭」đọc là gì?",
        "options": [
          { "optionId": "A", "text": "あたま", "isCorrect": true },
          { "optionId": "B", "text": "かお", "isCorrect": false },
          { "optionId": "C", "text": "め", "isCorrect": false },
          { "optionId": "D", "text": "はな", "isCorrect": false }
        ],
        "correctAnswer": "A",
        "explanation": "頭 (あたま) có nghĩa là đầu",
        "points": 10,
        "difficulty": 1
      },
      {
        "_id": { "$oid": "693e36d08bebd27195925003" },
        "questionNumber": 2,
        "questionType": "MULTIPLE_CHOICE",
        "questionText": "「目」có nghĩa là gì?",
        "options": [
          { "optionId": "A", "text": "Tai", "isCorrect": false },
          { "optionId": "B", "text": "Mắt", "isCorrect": true },
          { "optionId": "C", "text": "Mũi", "isCorrect": false },
          { "optionId": "D", "text": "Miệng", "isCorrect": false }
        ],
        "correctAnswer": "B",
        "explanation": "目 (め) có nghĩa là mắt",
        "points": 10,
        "difficulty": 1
      },
      {
        "_id": { "$oid": "693e36d08bebd27195925004" },
        "questionNumber": 3,
        "questionType": "TRUE_FALSE",
        "questionText": "「耳」(みみ) có nghĩa là tai",
        "options": [
          { "optionId": "A", "text": "Đúng", "isCorrect": true },
          { "optionId": "B", "text": "Sai", "isCorrect": false }
        ],
        "correctAnswer": "A",
        "explanation": "耳 (みみ) đúng là có nghĩa là tai",
        "points": 10,
        "difficulty": 1
      },
      {
        "_id": { "$oid": "693e36d08bebd27195925005" },
        "questionNumber": 4,
        "questionType": "MULTIPLE_CHOICE",
        "questionText": "「口」đọc là gì?",
        "options": [
          { "optionId": "A", "text": "くち", "isCorrect": true },
          { "optionId": "B", "text": "はな", "isCorrect": false },
          { "optionId": "C", "text": "した", "isCorrect": false },
          { "optionId": "D", "text": "は", "isCorrect": false }
        ],
        "correctAnswer": "A",
        "explanation": "口 (くち) có nghĩa là miệng",
        "points": 10,
        "difficulty": 1
      },
      {
        "_id": { "$oid": "693e36d08bebd27195925006" },
        "questionNumber": 5,
        "questionType": "MULTIPLE_CHOICE",
        "questionText": "Từ nào có nghĩa là 'tay'?",
        "options": [
          { "optionId": "A", "text": "足", "isCorrect": false },
          { "optionId": "B", "text": "手", "isCorrect": true },
          { "optionId": "C", "text": "指", "isCorrect": false },
          { "optionId": "D", "text": "腕", "isCorrect": false }
        ],
        "correctAnswer": "B",
        "explanation": "手 (て) có nghĩa là tay",
        "points": 10,
        "difficulty": 1
      },
      {
        "_id": { "$oid": "693e36d08bebd27195925007" },
        "questionNumber": 6,
        "questionType": "FILL_BLANK",
        "questionText": "___が痛いです。(chân)",
        "options": [
          { "optionId": "A", "text": "足", "isCorrect": true },
          { "optionId": "B", "text": "手", "isCorrect": false },
          { "optionId": "C", "text": "頭", "isCorrect": false },
          { "optionId": "D", "text": "目", "isCorrect": false }
        ],
        "correctAnswer": "A",
        "explanation": "足 (あし) có nghĩa là chân",
        "points": 10,
        "difficulty": 1
      },
      {
        "_id": { "$oid": "693e36d08bebd27195925008" },
        "questionNumber": 7,
        "questionType": "MULTIPLE_CHOICE",
        "questionText": "「鼻」có nghĩa là gì?",
        "options": [
          { "optionId": "A", "text": "Miệng", "isCorrect": false },
          { "optionId": "B", "text": "Mũi", "isCorrect": true },
          { "optionId": "C", "text": "Tai", "isCorrect": false },
          { "optionId": "D", "text": "Mắt", "isCorrect": false }
        ],
        "correctAnswer": "B",
        "explanation": "鼻 (はな) có nghĩa là mũi",
        "points": 10,
        "difficulty": 1
      },
      {
        "_id": { "$oid": "693e36d08bebd27195925009" },
        "questionNumber": 8,
        "questionType": "MULTIPLE_CHOICE",
        "questionText": "「顔」đọc là gì?",
        "options": [
          { "optionId": "A", "text": "かお", "isCorrect": true },
          { "optionId": "B", "text": "あたま", "isCorrect": false },
          { "optionId": "C", "text": "くび", "isCorrect": false },
          { "optionId": "D", "text": "かた", "isCorrect": false }
        ],
        "correctAnswer": "A",
        "explanation": "顔 (かお) có nghĩa là mặt/khuôn mặt",
        "points": 10,
        "difficulty": 1
      },
      {
        "_id": { "$oid": "693e36d08bebd2719592500a" },
        "questionNumber": 9,
        "questionType": "TRUE_FALSE",
        "questionText": "「歯」(は) có nghĩa là răng",
        "options": [
          { "optionId": "A", "text": "Đúng", "isCorrect": true },
          { "optionId": "B", "text": "Sai", "isCorrect": false }
        ],
        "correctAnswer": "A",
        "explanation": "歯 (は) đúng là có nghĩa là răng",
        "points": 10,
        "difficulty": 1
      },
      {
        "_id": { "$oid": "693e36d08bebd2719592500b" },
        "questionNumber": 10,
        "questionType": "MULTIPLE_CHOICE",
        "questionText": "Từ nào có nghĩa là 'bụng'?",
        "options": [
          { "optionId": "A", "text": "背中", "isCorrect": false },
          { "optionId": "B", "text": "お腹", "isCorrect": true },
          { "optionId": "C", "text": "胸", "isCorrect": false },
          { "optionId": "D", "text": "腰", "isCorrect": false }
        ],
        "correctAnswer": "B",
        "explanation": "お腹 (おなか) có nghĩa là bụng",
        "points": 10,
        "difficulty": 1
      }
    ],
    "settings": {
      "totalQuestions": 10,
      "passingScore": 70,
      "shuffleQuestions": true,
      "shuffleOptions": true,
      "showExplanation": true,
      "allowRetry": true
    },
    "statistics": { "totalAttempts": 0, "averageScore": 0, "passRate": 0 },
    "isActive": true,
    "isPublished": true,
    "createdAt": { "$date": "2025-12-14T04:02:24.022Z" },
    "updatedAt": { "$date": "2025-12-14T04:02:24.022Z" }
  },
  {
    "_id": { "$oid": "693e36d08bebd27195925010" },
    "topic": "BODY_PARTS",
    "level": "N4",
    "setNumber": 1,
    "title": "Bộ phận cơ thể - Sơ cấp",
    "description": "Bộ câu hỏi BODY_PARTS cấp độ N4",
    "questions": [
      {
        "_id": { "$oid": "693e36d08bebd27195925011" },
        "questionNumber": 1,
        "questionType": "MULTIPLE_CHOICE",
        "questionText": "「首」đọc là gì?",
        "options": [
          { "optionId": "A", "text": "くび", "isCorrect": true },
          { "optionId": "B", "text": "かた", "isCorrect": false },
          { "optionId": "C", "text": "むね", "isCorrect": false },
          { "optionId": "D", "text": "こし", "isCorrect": false }
        ],
        "correctAnswer": "A",
        "explanation": "首 (くび) có nghĩa là cổ",
        "points": 10,
        "difficulty": 2
      },
      {
        "_id": { "$oid": "693e36d08bebd27195925012" },
        "questionNumber": 2,
        "questionType": "MULTIPLE_CHOICE",
        "questionText": "「肩」có nghĩa là gì?",
        "options": [
          { "optionId": "A", "text": "Cổ", "isCorrect": false },
          { "optionId": "B", "text": "Vai", "isCorrect": true },
          { "optionId": "C", "text": "Lưng", "isCorrect": false },
          { "optionId": "D", "text": "Ngực", "isCorrect": false }
        ],
        "correctAnswer": "B",
        "explanation": "肩 (かた) có nghĩa là vai",
        "points": 10,
        "difficulty": 2
      },
      {
        "_id": { "$oid": "693e36d08bebd27195925013" },
        "questionNumber": 3,
        "questionType": "FILL_BLANK",
        "questionText": "___が凝っています。(vai)",
        "options": [
          { "optionId": "A", "text": "肩", "isCorrect": true },
          { "optionId": "B", "text": "首", "isCorrect": false },
          { "optionId": "C", "text": "腰", "isCorrect": false },
          { "optionId": "D", "text": "背中", "isCorrect": false }
        ],
        "correctAnswer": "A",
        "explanation": "肩が凝る (かたがこる) nghĩa là bị mỏi vai",
        "points": 10,
        "difficulty": 2
      },
      {
        "_id": { "$oid": "693e36d08bebd27195925014" },
        "questionNumber": 4,
        "questionType": "MULTIPLE_CHOICE",
        "questionText": "「背中」đọc là gì?",
        "options": [
          { "optionId": "A", "text": "せなか", "isCorrect": true },
          { "optionId": "B", "text": "はいちゅう", "isCorrect": false },
          { "optionId": "C", "text": "そなか", "isCorrect": false },
          { "optionId": "D", "text": "せちゅう", "isCorrect": false }
        ],
        "correctAnswer": "A",
        "explanation": "背中 (せなか) có nghĩa là lưng",
        "points": 10,
        "difficulty": 2
      },
      {
        "_id": { "$oid": "693e36d08bebd27195925015" },
        "questionNumber": 5,
        "questionType": "TRUE_FALSE",
        "questionText": "「腕」(うで) có nghĩa là cánh tay",
        "options": [
          { "optionId": "A", "text": "Đúng", "isCorrect": true },
          { "optionId": "B", "text": "Sai", "isCorrect": false }
        ],
        "correctAnswer": "A",
        "explanation": "腕 (うで) đúng là có nghĩa là cánh tay",
        "points": 10,
        "difficulty": 2
      },
      {
        "_id": { "$oid": "693e36d08bebd27195925016" },
        "questionNumber": 6,
        "questionType": "MULTIPLE_CHOICE",
        "questionText": "「指」có nghĩa là gì?",
        "options": [
          { "optionId": "A", "text": "Bàn tay", "isCorrect": false },
          { "optionId": "B", "text": "Ngón tay", "isCorrect": true },
          { "optionId": "C", "text": "Cổ tay", "isCorrect": false },
          { "optionId": "D", "text": "Khuỷu tay", "isCorrect": false }
        ],
        "correctAnswer": "B",
        "explanation": "指 (ゆび) có nghĩa là ngón tay",
        "points": 10,
        "difficulty": 2
      },
      {
        "_id": { "$oid": "693e36d08bebd27195925017" },
        "questionNumber": 7,
        "questionType": "MULTIPLE_CHOICE",
        "questionText": "「膝」đọc là gì?",
        "options": [
          { "optionId": "A", "text": "ひざ", "isCorrect": true },
          { "optionId": "B", "text": "ひじ", "isCorrect": false },
          { "optionId": "C", "text": "あし", "isCorrect": false },
          { "optionId": "D", "text": "こし", "isCorrect": false }
        ],
        "correctAnswer": "A",
        "explanation": "膝 (ひざ) có nghĩa là đầu gối",
        "points": 10,
        "difficulty": 2
      },
      {
        "_id": { "$oid": "693e36d08bebd27195925018" },
        "questionNumber": 8,
        "questionType": "FILL_BLANK",
        "questionText": "___を曲げてください。(khuỷu tay)",
        "options": [
          { "optionId": "A", "text": "肘", "isCorrect": true },
          { "optionId": "B", "text": "膝", "isCorrect": false },
          { "optionId": "C", "text": "腕", "isCorrect": false },
          { "optionId": "D", "text": "手首", "isCorrect": false }
        ],
        "correctAnswer": "A",
        "explanation": "肘 (ひじ) có nghĩa là khuỷu tay",
        "points": 10,
        "difficulty": 2
      },
      {
        "_id": { "$oid": "693e36d08bebd27195925019" },
        "questionNumber": 9,
        "questionType": "MULTIPLE_CHOICE",
        "questionText": "「胸」có nghĩa là gì?",
        "options": [
          { "optionId": "A", "text": "Bụng", "isCorrect": false },
          { "optionId": "B", "text": "Ngực", "isCorrect": true },
          { "optionId": "C", "text": "Lưng", "isCorrect": false },
          { "optionId": "D", "text": "Eo", "isCorrect": false }
        ],
        "correctAnswer": "B",
        "explanation": "胸 (むね) có nghĩa là ngực",
        "points": 10,
        "difficulty": 2
      },
      {
        "_id": { "$oid": "693e36d08bebd2719592501a" },
        "questionNumber": 10,
        "questionType": "TRUE_FALSE",
        "questionText": "「腰」(こし) có nghĩa là eo/hông",
        "options": [
          { "optionId": "A", "text": "Đúng", "isCorrect": true },
          { "optionId": "B", "text": "Sai", "isCorrect": false }
        ],
        "correctAnswer": "A",
        "explanation": "腰 (こし) đúng là có nghĩa là eo/hông/thắt lưng",
        "points": 10,
        "difficulty": 2
      }
    ],
    "settings": {
      "totalQuestions": 10,
      "passingScore": 70,
      "shuffleQuestions": true,
      "shuffleOptions": true,
      "showExplanation": true,
      "allowRetry": true
    },
    "statistics": { "totalAttempts": 0, "averageScore": 0, "passRate": 0 },
    "isActive": true,
    "isPublished": true,
    "createdAt": { "$date": "2025-12-14T04:02:24.022Z" },
    "updatedAt": { "$date": "2025-12-14T04:02:24.022Z" }
  },
  {
    "_id": { "$oid": "693e36d08bebd27195925020" },
    "topic": "BODY_PARTS",
    "level": "N3",
    "setNumber": 1,
    "title": "Bộ phận cơ thể - Trung cấp",
    "description": "Bộ câu hỏi BODY_PARTS cấp độ N3",
    "questions": [
      {
        "_id": { "$oid": "693e36d08bebd27195925021" },
        "questionNumber": 1,
        "questionType": "MULTIPLE_CHOICE",
        "questionText": "「心臓」có nghĩa là gì?",
        "options": [
          { "optionId": "A", "text": "Phổi", "isCorrect": false },
          { "optionId": "B", "text": "Tim", "isCorrect": true },
          { "optionId": "C", "text": "Gan", "isCorrect": false },
          { "optionId": "D", "text": "Dạ dày", "isCorrect": false }
        ],
        "correctAnswer": "B",
        "explanation": "心臓 (しんぞう) có nghĩa là tim/trái tim",
        "points": 15,
        "difficulty": 3
      },
      {
        "_id": { "$oid": "693e36d08bebd27195925022" },
        "questionNumber": 2,
        "questionType": "MULTIPLE_CHOICE",
        "questionText": "「肺」đọc là gì?",
        "options": [
          { "optionId": "A", "text": "はい", "isCorrect": true },
          { "optionId": "B", "text": "かん", "isCorrect": false },
          { "optionId": "C", "text": "い", "isCorrect": false },
          { "optionId": "D", "text": "ちょう", "isCorrect": false }
        ],
        "correctAnswer": "A",
        "explanation": "肺 (はい) có nghĩa là phổi",
        "points": 15,
        "difficulty": 3
      },
      {
        "_id": { "$oid": "693e36d08bebd27195925023" },
        "questionNumber": 3,
        "questionType": "FILL_BLANK",
        "questionText": "___の検査を受けました。(gan)",
        "options": [
          { "optionId": "A", "text": "肝臓", "isCorrect": true },
          { "optionId": "B", "text": "心臓", "isCorrect": false },
          { "optionId": "C", "text": "腎臓", "isCorrect": false },
          { "optionId": "D", "text": "胃", "isCorrect": false }
        ],
        "correctAnswer": "A",
        "explanation": "肝臓 (かんぞう) có nghĩa là gan",
        "points": 15,
        "difficulty": 3
      },
      {
        "_id": { "$oid": "693e36d08bebd27195925024" },
        "questionNumber": 4,
        "questionType": "MULTIPLE_CHOICE",
        "questionText": "「筋肉」có nghĩa là gì?",
        "options": [
          { "optionId": "A", "text": "Xương", "isCorrect": false },
          { "optionId": "B", "text": "Cơ bắp", "isCorrect": true },
          { "optionId": "C", "text": "Da", "isCorrect": false },
          { "optionId": "D", "text": "Gân", "isCorrect": false }
        ],
        "correctAnswer": "B",
        "explanation": "筋肉 (きんにく) có nghĩa là cơ bắp",
        "points": 15,
        "difficulty": 3
      },
      {
        "_id": { "$oid": "693e36d08bebd27195925025" },
        "questionNumber": 5,
        "questionType": "TRUE_FALSE",
        "questionText": "「骨」(ほね) có nghĩa là xương",
        "options": [
          { "optionId": "A", "text": "Đúng", "isCorrect": true },
          { "optionId": "B", "text": "Sai", "isCorrect": false }
        ],
        "correctAnswer": "A",
        "explanation": "骨 (ほね) đúng là có nghĩa là xương",
        "points": 15,
        "difficulty": 3
      }
    ],
    "settings": {
      "totalQuestions": 5,
      "passingScore": 70,
      "shuffleQuestions": true,
      "shuffleOptions": true,
      "showExplanation": true,
      "allowRetry": true
    },
    "statistics": { "totalAttempts": 0, "averageScore": 0, "passRate": 0 },
    "isActive": true,
    "isPublished": true,
    "createdAt": { "$date": "2025-12-14T04:02:24.022Z" },
    "updatedAt": { "$date": "2025-12-14T04:02:24.022Z" }
  },
  {
    "_id": { "$oid": "693e36d08bebd27195925030" },
    "topic": "BODY_PARTS",
    "level": "N2",
    "setNumber": 1,
    "title": "Bộ phận cơ thể - Trung cao cấp",
    "description": "Bộ câu hỏi BODY_PARTS cấp độ N2",
    "questions": [
      {
        "_id": { "$oid": "693e36d08bebd27195925031" },
        "questionNumber": 1,
        "questionType": "MULTIPLE_CHOICE",
        "questionText": "「脊椎」có nghĩa là gì?",
        "options": [
          { "optionId": "A", "text": "Xương sườn", "isCorrect": false },
          { "optionId": "B", "text": "Cột sống", "isCorrect": true },
          { "optionId": "C", "text": "Xương chậu", "isCorrect": false },
          { "optionId": "D", "text": "Xương đòn", "isCorrect": false }
        ],
        "correctAnswer": "B",
        "explanation": "脊椎 (せきつい) có nghĩa là cột sống",
        "points": 20,
        "difficulty": 4
      },
      {
        "_id": { "$oid": "693e36d08bebd27195925032" },
        "questionNumber": 2,
        "questionType": "MULTIPLE_CHOICE",
        "questionText": "「血管」đọc là gì?",
        "options": [
          { "optionId": "A", "text": "けっかん", "isCorrect": true },
          { "optionId": "B", "text": "ちかん", "isCorrect": false },
          { "optionId": "C", "text": "けつかん", "isCorrect": false },
          { "optionId": "D", "text": "ちけつ", "isCorrect": false }
        ],
        "correctAnswer": "A",
        "explanation": "血管 (けっかん) có nghĩa là mạch máu",
        "points": 20,
        "difficulty": 4
      },
      {
        "_id": { "$oid": "693e36d08bebd27195925033" },
        "questionNumber": 3,
        "questionType": "FILL_BLANK",
        "questionText": "___の働きが低下している。(thận)",
        "options": [
          { "optionId": "A", "text": "腎臓", "isCorrect": true },
          { "optionId": "B", "text": "肝臓", "isCorrect": false },
          { "optionId": "C", "text": "心臓", "isCorrect": false },
          { "optionId": "D", "text": "脾臓", "isCorrect": false }
        ],
        "correctAnswer": "A",
        "explanation": "腎臓 (じんぞう) có nghĩa là thận",
        "points": 20,
        "difficulty": 4
      },
      {
        "_id": { "$oid": "693e36d08bebd27195925034" },
        "questionNumber": 4,
        "questionType": "MULTIPLE_CHOICE",
        "questionText": "「神経」có nghĩa là gì?",
        "options": [
          { "optionId": "A", "text": "Mạch máu", "isCorrect": false },
          { "optionId": "B", "text": "Dây thần kinh", "isCorrect": true },
          { "optionId": "C", "text": "Cơ bắp", "isCorrect": false },
          { "optionId": "D", "text": "Gân", "isCorrect": false }
        ],
        "correctAnswer": "B",
        "explanation": "神経 (しんけい) có nghĩa là dây thần kinh",
        "points": 20,
        "difficulty": 4
      }
    ],
    "settings": {
      "totalQuestions": 4,
      "passingScore": 70,
      "shuffleQuestions": true,
      "shuffleOptions": true,
      "showExplanation": true,
      "allowRetry": true
    },
    "statistics": { "totalAttempts": 0, "averageScore": 0, "passRate": 0 },
    "isActive": true,
    "isPublished": true,
    "createdAt": { "$date": "2025-12-14T04:02:24.022Z" },
    "updatedAt": { "$date": "2025-12-14T04:02:24.022Z" }
  },
  {
    "_id": { "$oid": "693e36d08bebd27195925040" },
    "topic": "BODY_PARTS",
    "level": "N1",
    "setNumber": 1,
    "title": "Bộ phận cơ thể - Cao cấp",
    "description": "Bộ câu hỏi BODY_PARTS cấp độ N1",
    "questions": [
      {
        "_id": { "$oid": "693e36d08bebd27195925041" },
        "questionNumber": 1,
        "questionType": "MULTIPLE_CHOICE",
        "questionText": "「延髄」có nghĩa là gì?",
        "options": [
          { "optionId": "A", "text": "Tiểu não", "isCorrect": false },
          { "optionId": "B", "text": "Hành não", "isCorrect": true },
          { "optionId": "C", "text": "Đại não", "isCorrect": false },
          { "optionId": "D", "text": "Tủy sống", "isCorrect": false }
        ],
        "correctAnswer": "B",
        "explanation": "延髄 (えんずい) có nghĩa là hành não (phần dưới cùng của não)",
        "points": 25,
        "difficulty": 5
      },
      {
        "_id": { "$oid": "693e36d08bebd27195925042" },
        "questionNumber": 2,
        "questionType": "MULTIPLE_CHOICE",
        "questionText": "「膵臓」đọc là gì?",
        "options": [
          { "optionId": "A", "text": "すいぞう", "isCorrect": true },
          { "optionId": "B", "text": "ひぞう", "isCorrect": false },
          { "optionId": "C", "text": "かんぞう", "isCorrect": false },
          { "optionId": "D", "text": "じんぞう", "isCorrect": false }
        ],
        "correctAnswer": "A",
        "explanation": "膵臓 (すいぞう) có nghĩa là tuyến tụy",
        "points": 25,
        "difficulty": 5
      },
      {
        "_id": { "$oid": "693e36d08bebd27195925043" },
        "questionNumber": 3,
        "questionType": "FILL_BLANK",
        "questionText": "___は免疫機能に重要な役割を果たす。(tuyến ức)",
        "options": [
          { "optionId": "A", "text": "胸腺", "isCorrect": true },
          { "optionId": "B", "text": "甲状腺", "isCorrect": false },
          { "optionId": "C", "text": "副腎", "isCorrect": false },
          { "optionId": "D", "text": "脾臓", "isCorrect": false }
        ],
        "correctAnswer": "A",
        "explanation": "胸腺 (きょうせん) có nghĩa là tuyến ức, quan trọng cho hệ miễn dịch",
        "points": 25,
        "difficulty": 5
      }
    ],
    "settings": {
      "totalQuestions": 3,
      "passingScore": 70,
      "shuffleQuestions": true,
      "shuffleOptions": true,
      "showExplanation": true,
      "allowRetry": true
    },
    "statistics": { "totalAttempts": 0, "averageScore": 0, "passRate": 0 },
    "isActive": true,
    "isPublished": true,
    "createdAt": { "$date": "2025-12-14T04:02:24.022Z" },
    "updatedAt": { "$date": "2025-12-14T04:02:24.022Z" }
  }
]
